py_git_assistant/__init__.py
py_git_assistant/assistant.py
py_git_assistant/services/__init__.py
py_git_assistant/services/git_service.py
py_git_assistant/services/ui_service.py
py_git_assistant/utils/__init__.py
py_git_assistant/utils/helpers.py
py_git_assistant-0.1.2.dist-info/METADATA
py_git_assistant-0.1.2.dist-info/WHEEL
py_git_assistant-0.1.2.dist-info/entry_points.txt
py_git_assistant-0.1.2.dist-info/top_level.txt
py_git_assistant-0.1.2.dist-info/RECORD
