Metadata-Version: 2.4
Name: py-git-assistant
Version: 0.1.2
Summary: A simple CLI tool to assist with common Git operations.
Author-email: Kelwyn Oliveira <sksoliveira.eng@gmail.com>
License-Expression: MIT
Project-URL: Homepage, https://github.com/kelwynoliveira/py_git_assistant
Requires-Python: >=3.8
Requires-Dist: questionary>=2.1.0
Requires-Dist: colorama>=0.4.6
